Metadata-Version: 2.1
Name: pydoit
Version: 0.0.1
Summary: An API Wrapper around the i-doit API
Home-page: https://github.com/aaronlyy/pydoit
Author: Aaron Levi Can (aaronlyy)
Author-email: aaronlevican@gmail.com
License: GPL-3.0 License
Download-URL: https://github.com/aaronlyy/pydoit/archive/v0.0.1.tar.gz
Keywords: api,wrapper,json,jsonrpc,http
Platform: UNKNOWN
